.configs/arch-torrc
.configs/centos-torrc
.configs/debian-torrc
.configs/fedora-torrc
.configs/void-torrc
nipe_py/__init__.py
nipe_py/main.py
nipe_py/py.typed
nipe_py/engine/Restart.py
nipe_py/engine/Start.py
nipe_py/engine/Stop.py
nipe_py/utils/Device.py
nipe_py/utils/Install.py
nipe_py/utils/Status.py
nipe_py-0.1.6.dist-info/METADATA
nipe_py-0.1.6.dist-info/WHEEL
nipe_py-0.1.6.dist-info/entry_points.txt
nipe_py-0.1.6.dist-info/licenses/LICENSE
nipe_py-0.1.6.dist-info/RECORD
