Metadata-Version: 2.3
Name: nipe_py
Version: 0.1.6
Summary: An engine to make Tor Network your default gateway.
Project-URL: Documentation, https://aviksaikat.github.io/nipe_py/
Project-URL: Source, https://github.com/aviksaikat/nipe_py
Author-email: nipe_py <github.maturity983@passinbox.com>
License: MIT License
License-File: LICENSE
Classifier: Programming Language :: Python
Classifier: Programming Language :: Python :: 3 :: Only
Classifier: Programming Language :: Python :: 3.9
Classifier: Programming Language :: Python :: 3.10
Classifier: Programming Language :: Python :: 3.11
Classifier: Programming Language :: Python :: 3.12
Classifier: Programming Language :: Python :: Implementation :: CPython
Classifier: Programming Language :: Python :: Implementation :: PyPy
Requires-Python: >=3.9
Requires-Dist: click
Requires-Dist: requests
Requires-Dist: rich
